[{
"label": "Teodoro Ramírez P.", "lat": 30.607418, "lng": -111.019198
},{
"label": "La Lomita (Buena Vista)", "lat": 30.586998, "lng": -110.908864
},{
"label": "Ninguno [Familia García]", "lat": 30.619608, "lng": -111.009846
},{
"label": "El Yeso", "lat": 30.581621, "lng": -110.840991
},{
"label": "San Francisco II", "lat": 30.754796, "lng": -111.187121
},{
"label": "Santa Elia", "lat": 30.600269, "lng": -110.936103
},{
"label": "San Lázaro", "lat": 30.803811, "lng": -111.206646
},{
"label": "El Vado", "lat": 30.562229, "lng": -110.869269
},{
"label": "El Pecado", "lat": 30.687517, "lng": -110.937148
},{
"label": "Los Caporales", "lat": 30.622933, "lng": -111.011231
},{
"label": "El Carrizo", "lat": 30.795427, "lng": -111.203364
},{
"label": "Jesús Fraijo", "lat": 30.666869, "lng": -111.021056
},{
"label": "Juan Contreras", "lat": 30.604407, "lng": -110.937344
},{
"label": "Rene León Valenzuela", "lat": 30.737278, "lng": -111.158403
},{
"label": "Los Limones", "lat": 30.669563, "lng": -110.96604
},{
"label": "Ninguno [El Invernadero de los Flores]", "lat": 30.660278, "lng": -110.954722
},{
"label": "La Curva", "lat": 30.603297, "lng": -110.939156
},{
"label": "Ramón Mendivil", "lat": 30.695514, "lng": -110.955876
},{
"label": "Los Chinos", "lat": 30.780292, "lng": -111.205366
},{
"label": "Manuel Morales", "lat": 30.586806, "lng": -110.909903
},{
"label": "Lizárraga (La Galera)", "lat": 30.617222, "lng": -111.089722
},{
"label": "El Diecinueve", "lat": 30.650891, "lng": -110.949132
},{
"label": "Villa Fontana", "lat": 30.655174, "lng": -111.146264
},{
"label": "Los Pozos Viejos", "lat": 30.662327, "lng": -110.90335
},{
"label": "Fredeberto León", "lat": 30.761405, "lng": -111.179167
},{
"label": "Martín Vicente Martínez Pino", "lat": 30.614091, "lng": -110.93145
},{
"label": "Santa Amalia", "lat": 30.561612, "lng": -110.871549
},{
"label": "Las Playas", "lat": 30.730156, "lng": -111.15918
},{
"label": "San Luis", "lat": 30.664712, "lng": -110.885069
},{
"label": "Familia Celaya", "lat": 30.734024, "lng": -111.162836
},{
"label": "Javier Islava", "lat": 30.588172, "lng": -110.965681
},{
"label": "San Marcial", "lat": 30.559977, "lng": -110.894125
},{
"label": "El Alamito", "lat": 30.66102, "lng": -111.019625
},{
"label": "Santa Fe", "lat": 30.607794, "lng": -111.010495
},{
"label": "Heriberto León Valenzuela", "lat": 30.744476, "lng": -111.152691
},{
"label": "Rigoberto Parra", "lat": 30.743836, "lng": -111.177575
},{
"label": "Ninguno", "lat": 30.854731, "lng": -111.106076
},{
"label": "La Bellota", "lat": 30.547519, "lng": -110.824869
},{
"label": "El Tascalito", "lat": 30.582482, "lng": -110.904483
},{
"label": "Humberto Castro Martínez", "lat": 30.670019, "lng": -111.121221
},{
"label": "San Agustín", "lat": 30.758378, "lng": -111.143468
},{
"label": "El Represo", "lat": 30.659532, "lng": -110.956782
},{
"label": "La Agüita", "lat": 30.909725, "lng": -111.048565
},{
"label": "Guadalupe", "lat": 30.590295, "lng": -110.919895
},{
"label": "Los Pimientos", "lat": 30.66783, "lng": -110.883028
},{
"label": "La Cuesta", "lat": 30.885693, "lng": -111.093117
},{
"label": "Casa Blanca", "lat": 30.595939, "lng": -110.931268
},{
"label": "Hector G. López", "lat": 30.608509, "lng": -111.016431
},{
"label": "Las Praderas", "lat": 30.544862, "lng": -110.919867
},{
"label": "Magdalena de Kino", "lat": 30.630356, "lng": -110.969404
},{
"label": "Santa Clara", "lat": 30.70266, "lng": -111.141759
},{
"label": "Rafael Ortega", "lat": 30.772112, "lng": -111.132325
},{
"label": "La Galera", "lat": 30.652422, "lng": -110.964177
},{
"label": "Ramón Mezquita Ortiz", "lat": 30.694393, "lng": -111.028407
},{
"label": "El Ojo de Agua", "lat": 30.484981, "lng": -110.839049
},{
"label": "El Sahuarito", "lat": 30.770278, "lng": -111.113056
},{
"label": "El Encino", "lat": 31.004147, "lng": -111.216134
},{
"label": "San Carlos", "lat": 30.597818, "lng": -110.927331
},{
"label": "Rey David Villanueva", "lat": 30.662813, "lng": -111.018491
},{
"label": "Enrique Ruiz", "lat": 30.575326, "lng": -110.906239
},{
"label": "Tierra de los Leones", "lat": 30.689841, "lng": -110.937474
},{
"label": "Murrieta", "lat": 30.689554, "lng": -111.146516
},{
"label": "Valenzuela [Partes Usadas]", "lat": 30.609177, "lng": -110.946915
},{
"label": "San Enrique", "lat": 30.66775, "lng": -110.870747
},{
"label": "El Tejanito", "lat": 30.527178, "lng": -110.884878
},{
"label": "Los Nogales (Los Nogales Viejos)", "lat": 30.870556, "lng": -111.100833
},{
"label": "El Cargadero", "lat": 30.6446, "lng": -110.810571
},{
"label": "El Tapiro", "lat": 30.589407, "lng": -110.918888
},{
"label": "El Maguey", "lat": 30.801843, "lng": -111.115498
},{
"label": "Familia Orcí", "lat": 30.612778, "lng": -111.003703
},{
"label": "La Aguja", "lat": 30.589308, "lng": -110.864909
},{
"label": "González", "lat": 30.591062, "lng": -110.919146
},{
"label": "El Abundio", "lat": 30.60831, "lng": -110.944394
},{
"label": "San Ignacio", "lat": 30.696647, "lng": -110.924021
},{
"label": "Barrio Rastro Final (Divisaderos)", "lat": 30.610246, "lng": -110.958228
},{
"label": "El Infierno", "lat": 30.737946, "lng": -111.145486
},{
"label": "Tres Hermanos", "lat": 30.587592, "lng": -110.912092
},{
"label": "Industrias Materias Primas", "lat": 30.593372, "lng": -110.981867
},{
"label": "El Pocito", "lat": 30.666981, "lng": -110.873274
},{
"label": "El Rincón", "lat": 30.927812, "lng": -111.06477
},{
"label": "Los Olmos", "lat": 30.760362, "lng": -111.140526
},{
"label": "La Tésota", "lat": 30.69417, "lng": -110.965914
},{
"label": "Rancho de Peralta", "lat": 30.678981, "lng": -111.020656
},{
"label": "Rancho López (Arredondo)", "lat": 31.001041, "lng": -111.125421
},{
"label": "La Angostura", "lat": 30.590743, "lng": -111.048895
},{
"label": "El Echadero", "lat": 30.67151, "lng": -110.949988
},{
"label": "Socorro Navidad", "lat": 30.615836, "lng": -110.97229
},{
"label": "El Basaitec", "lat": 30.678377, "lng": -110.949312
},{
"label": "Raul Sainz", "lat": 30.585951, "lng": -110.906469
},{
"label": "El Toji", "lat": 30.749888, "lng": -111.197257
},{
"label": "Buenaventura (El Duende)", "lat": 30.66639, "lng": -111.148554
},{
"label": "La Presita", "lat": 30.6625, "lng": -110.868333
},{
"label": "Héctor Trujillo", "lat": 30.669709, "lng": -111.018292
},{
"label": "El Jacalito", "lat": 30.700905, "lng": -111.034466
},{
"label": "Ninguno [Cervantes Aguirre Sony]", "lat": 30.607548, "lng": -111.050749
},{
"label": "Las Mochas", "lat": 30.560801, "lng": -110.878684
},{
"label": "Rancho de Fernando Esquer", "lat": 30.559443, "lng": -110.870048
},{
"label": "La Mirandeña", "lat": 30.602261, "lng": -111.049158
},{
"label": "Ignacio Contreras", "lat": 30.579235, "lng": -110.909052
},{
"label": "Santa Regina", "lat": 30.595419, "lng": -111.038936
},{
"label": "El Aguajito", "lat": 30.939981, "lng": -111.081101
},{
"label": "San Lázaro (Las Borregas)", "lat": 30.697302, "lng": -110.958318
},{
"label": "Las Orquídeas", "lat": 30.663255, "lng": -110.868518
},{
"label": "La Cebolla", "lat": 30.743314, "lng": -111.158184
},{
"label": "Guillermo Grijalva Piñuelas", "lat": 30.70111, "lng": -111.033814
},{
"label": "Barrio de los Robles", "lat": 30.591917, "lng": -110.927787
},{
"label": "El Divisadero", "lat": 30.599091, "lng": -110.928157
},{
"label": "El Portón", "lat": 30.613462, "lng": -110.920409
},{
"label": "Los Pinos", "lat": 30.738716, "lng": -111.146443
},{
"label": "Pimería", "lat": 30.609337, "lng": -110.958428
},{
"label": "El Centenario", "lat": 30.654996, "lng": -110.947904
},{
"label": "Rubén Pino Soberanes", "lat": 30.689085, "lng": -111.024845
},{
"label": "Reynaldo Figueroa", "lat": 30.576741, "lng": -110.902007
},{
"label": "Los Peñasquitos", "lat": 30.666913, "lng": -110.848674
},{
"label": "El Sahuaro", "lat": 30.744181, "lng": -111.193687
},{
"label": "José Álvaro Miranda Castro", "lat": 30.666561, "lng": -111.127395
},{
"label": "Rubén Pérez", "lat": 30.686154, "lng": -110.921897
},{
"label": "El Peñasco Colorado", "lat": 30.60926, "lng": -111.004786
},{
"label": "Los Nogales", "lat": 30.872726, "lng": -111.098957
},{
"label": "Rancho Viejo", "lat": 30.784223, "lng": -111.124538
},{
"label": "La Milpa", "lat": 30.606544, "lng": -110.944472
},{
"label": "Agua Dulce", "lat": 30.744967, "lng": -111.021229
},{
"label": "La Gallinera", "lat": 30.733172, "lng": -111.163132
},{
"label": "Buelna", "lat": 30.688836, "lng": -110.940414
},{
"label": "San Martín", "lat": 30.753141, "lng": -111.131551
},{
"label": "Los Nopales", "lat": 31.033333, "lng": -111.172778
},{
"label": "Martín Andrade Moreno", "lat": 30.611432, "lng": -110.922873
},{
"label": "Familia Valenzuela Tanori", "lat": 30.737288, "lng": -111.200892
},{
"label": "Lizarraga", "lat": 30.592205, "lng": -111.089626
},{
"label": "El Durazno", "lat": 30.77632, "lng": -111.18734
},{
"label": "El Abandonado", "lat": 30.75331, "lng": -111.150387
},{
"label": "El Saucito", "lat": 30.607811, "lng": -110.939704
},{
"label": "Charco Hondo", "lat": 30.767689, "lng": -111.133559
},{
"label": "Antonio Avechuco Quilahui", "lat": 30.590283, "lng": -110.920578
},{
"label": "El Sacrificio", "lat": 30.73436, "lng": -111.160973
},{
"label": "La Biznaga", "lat": 30.762055, "lng": -111.127187
},{
"label": "Cañada del Corral (Los Anillos)", "lat": 30.679278, "lng": -110.968994
},{
"label": "Rancho del Toro", "lat": 30.590568, "lng": -110.917929
},{
"label": "Rancho de Tomás", "lat": 30.676307, "lng": -110.964401
},{
"label": "José Ortega", "lat": 30.798839, "lng": -111.119167
},{
"label": "San Lorenzo la Angostura", "lat": 30.596468, "lng": -111.03364
},{
"label": "Los Fresnos", "lat": 30.605561, "lng": -111.023334
},{
"label": "Familia Tanori Morales", "lat": 30.734389, "lng": -111.173274
},{
"label": "El Coyote", "lat": 30.731589, "lng": -111.190903
},{
"label": "San Francisco", "lat": 30.756722, "lng": -111.173693
},{
"label": "El Jurahui", "lat": 30.887112, "lng": -111.0434
},{
"label": "San Manuel", "lat": 30.679419, "lng": -110.816654
},{
"label": "Tito León", "lat": 30.745113, "lng": -111.142611
},{
"label": "El Carrizo (Sotomayor)", "lat": 30.935169, "lng": -111.13406
},{
"label": "Corrales el Santo Niño", "lat": 30.602245, "lng": -110.92749
},{
"label": "La Capilla", "lat": 30.690395, "lng": -110.941731
},{
"label": "Familia Romo", "lat": 30.595779, "lng": -111.038009
},{
"label": "Las Rastras", "lat": 31.054456, "lng": -111.175925
},{
"label": "El Moisa", "lat": 30.669438, "lng": -111.015611
},{
"label": "Alma Fuentes", "lat": 30.59642, "lng": -110.926396
},{
"label": "Las Mesteñas", "lat": 30.53738, "lng": -110.907686
},{
"label": "Familia Carrillo", "lat": 30.603878, "lng": -111.020781
},{
"label": "Las Avispas", "lat": 30.771095, "lng": -111.232723
},{
"label": "Raúl Osorio", "lat": 30.609078, "lng": -110.945498
},{
"label": "El Sauz", "lat": 30.558639, "lng": -110.890378
},{
"label": "El Pino", "lat": 30.780157, "lng": -111.185396
},{
"label": "José Durazo Moreno", "lat": 30.596442, "lng": -111.036317
},{
"label": "El Jotaiqui", "lat": 30.983648, "lng": -111.169302
},{
"label": "Los Chirriones", "lat": 30.872211, "lng": -111.0935
},{
"label": "Huerta de los Gavino", "lat": 30.616048, "lng": -111.020492
},{
"label": "Buenavista", "lat": 30.690995, "lng": -110.951246
},{
"label": "Jesús Nacamura", "lat": 30.820571, "lng": -111.192113
},{
"label": "Francisco Ruben Coronado", "lat": 30.612705, "lng": -110.953971
},{
"label": "Jesús Castro Moreno", "lat": 30.67085, "lng": -111.126193
},{
"label": "La Granadita", "lat": 30.777222, "lng": -111.181944
},{
"label": "San Isidro", "lat": 30.690063, "lng": -110.940151
},{
"label": "La Joya", "lat": 30.841237, "lng": -111.081627
},{
"label": "Buena Vista", "lat": 30.726117, "lng": -111.152768
},{
"label": "El Recodo [Avícola]", "lat": 30.592059, "lng": -110.937004
},{
"label": "Eduardo Castro", "lat": 30.601704, "lng": -110.936514
},{
"label": "El Chinito", "lat": 30.778056, "lng": -111.218889
},{
"label": "La Coteña", "lat": 30.678873, "lng": -110.92884
},{
"label": "Nanenachi", "lat": 30.727263, "lng": -111.148081
},{
"label": "Las Peñitas", "lat": 30.688253, "lng": -110.926878
},{
"label": "San Lorenzo", "lat": 30.612457, "lng": -111.031881
},{
"label": "Raymundo González [El Negro]", "lat": 30.664992, "lng": -111.021284
},{
"label": "Potrero de Dávila", "lat": 30.589976, "lng": -110.93628
},{
"label": "La Amapoleña", "lat": 30.608914, "lng": -111.034211
},{
"label": "El Potrerito", "lat": 30.589694, "lng": -110.925861
},{
"label": "Padre Hoyos", "lat": 30.606633, "lng": -111.010413
},{
"label": "El Cinco", "lat": 30.645, "lng": -110.957778
},{
"label": "Pedro García", "lat": 30.656534, "lng": -110.923044
},{
"label": "La Escondida", "lat": 30.781745, "lng": -111.126046
},{
"label": "Guillermo Félix Parodi", "lat": 30.589615, "lng": -110.920881
},{
"label": "José María Valle Méndez", "lat": 30.772734, "lng": -111.185311
},{
"label": "Ramón Federico", "lat": 30.722686, "lng": -111.162629
},{
"label": "Chupadero", "lat": 30.564917, "lng": -110.961327
},{
"label": "Valle Verde", "lat": 30.692143, "lng": -110.941323
},{
"label": "El Álamo", "lat": 30.522032, "lng": -110.842432
},{
"label": "Ninguno [Magaña Ortiz]", "lat": 30.614921, "lng": -111.021344
},{
"label": "Las Palmas (Gruas Vélez)", "lat": 30.66056, "lng": -110.926594
},{
"label": "La Churea", "lat": 30.738318, "lng": -111.170059
},{
"label": "Familia Valenzuela", "lat": 30.73933, "lng": -111.200844
},{
"label": "La Mesa de Bedolla", "lat": 30.667154, "lng": -110.948596
},{
"label": "El Topahui", "lat": 30.679231, "lng": -111.152782
},{
"label": "El Calichi", "lat": 30.734388, "lng": -111.153051
},{
"label": "Rubén Romo Bejarano", "lat": 30.584099, "lng": -111.034162
},{
"label": "Loma Linda", "lat": 30.734449, "lng": -111.182866
},{
"label": "El Nogal", "lat": 30.555786, "lng": -110.892661
},{
"label": "El Ranchito", "lat": 30.673347, "lng": -110.949836
},{
"label": "Austreberto León", "lat": 30.747853, "lng": -111.139855
},{
"label": "Alfredo Hernández", "lat": 30.677625, "lng": -111.149408
},{
"label": "La Tinaja Colorada", "lat": 30.682629, "lng": -110.827934
},{
"label": "La Mesa del Álamo", "lat": 30.546016, "lng": -110.862917
},{
"label": "Las Cuevitas", "lat": 30.693079, "lng": -111.026884
},{
"label": "Bella Esperanza", "lat": 30.706159, "lng": -111.144861
},{
"label": "La Cebolla Vieja", "lat": 30.73777, "lng": -111.172661
},{
"label": "El Cúmaro", "lat": 30.768207, "lng": -111.169709
},{
"label": "Francisco Campillo", "lat": 30.789086, "lng": -111.118706
},{
"label": "Los Olivos", "lat": 30.592735, "lng": -110.930428
},{
"label": "La Natalia", "lat": 30.69271, "lng": -110.939613
},{
"label": "San Antonio", "lat": 30.703765, "lng": -110.979228
},{
"label": "San Francisco [Hacienda]", "lat": 30.679593, "lng": -110.942593
},{
"label": "Los Taraises", "lat": 30.58465, "lng": -110.87948
},{
"label": "Ismael Valenzuela", "lat": 30.587661, "lng": -110.913887
},{
"label": "La Cieneguita", "lat": 30.902641, "lng": -111.073107
},{
"label": "El Nopal", "lat": 30.593704, "lng": -110.853381
},{
"label": "Guadalupe Soto", "lat": 30.510816, "lng": -110.923298
},{
"label": "Gutiérrez (La Cebolla)", "lat": 30.757567, "lng": -111.144864
},{
"label": "Peñasco San Lorenzo", "lat": 30.606029, "lng": -111.013142
},{
"label": "Guillermo Martínez", "lat": 30.612352, "lng": -110.90059
},{
"label": "David Moreno", "lat": 30.609796, "lng": -110.903714
},{
"label": "La Tinaja Bonita", "lat": 30.486813, "lng": -110.873172
},{
"label": "La Tésota (El Fresno)", "lat": 30.776452, "lng": -111.202899
},{
"label": "El Carricito", "lat": 30.875569, "lng": -111.068841
},{
"label": "Las Grullas", "lat": 30.751358, "lng": -111.130346
},{
"label": "Martin Morales López", "lat": 30.736795, "lng": -111.200167
},{
"label": "La Nopalera", "lat": 30.686494, "lng": -111.024605
},{
"label": "La Lomita", "lat": 30.779478, "lng": -111.129097
},{
"label": "Familia Martínez", "lat": 30.673099, "lng": -111.148464
},{
"label": "El Cuadro", "lat": 30.605638, "lng": -111.047109
},{
"label": "La Laguna", "lat": 30.751374, "lng": -111.155715
},{
"label": "El Ombligo", "lat": 30.583786, "lng": -110.908758
},{
"label": "El Alto", "lat": 30.606531, "lng": -111.050975
},{
"label": "El Vallecito", "lat": 30.713067, "lng": -110.969961
},{
"label": "La Bermuda", "lat": 30.58153, "lng": -110.902853
},{
"label": "Rancho Irigoyen", "lat": 30.59868, "lng": -111.030789
},{
"label": "La Moreneña", "lat": 30.592619, "lng": -110.924745
},{
"label": "Los Cascabeles", "lat": 30.710495, "lng": -110.985787
},{
"label": "Juan Romo", "lat": 30.55369, "lng": -110.918961
},{
"label": "Salsipuedes", "lat": 30.546287, "lng": -110.896235
},{
"label": "Barrio la Choya de San Ignacio", "lat": 30.656632, "lng": -110.940186
},{
"label": "Los Morenos", "lat": 30.595865, "lng": -110.927154
},{
"label": "El Tecolote", "lat": 30.712353, "lng": -111.176917
},{
"label": "El Cuatro", "lat": 30.645209, "lng": -110.955684
},{
"label": "El Cajoncito", "lat": 30.512139, "lng": -110.858903
},{
"label": "Iván Javier León", "lat": 30.74879, "lng": -111.136018
},{
"label": "La Misión", "lat": 30.616618, "lng": -110.995725
},{
"label": "La Yaqui", "lat": 30.67953, "lng": -110.950988
},{
"label": "Rancho del Pelo Chino", "lat": 30.685601, "lng": -111.022203
},{
"label": "Las Caborqueñas", "lat": 30.60266, "lng": -110.814641
},{
"label": "Daniel Peralta", "lat": 30.608933, "lng": -111.01657
},{
"label": "Don Alberto", "lat": 30.669496, "lng": -110.942731
},{
"label": "La Ramada del Maestro", "lat": 30.656446, "lng": -110.919873
},{
"label": "El Recodo", "lat": 30.592583, "lng": -110.929126
},{
"label": "Juanita Guerrero", "lat": 30.558263, "lng": -110.891583
},{
"label": "El Chupadero", "lat": 31.062017, "lng": -111.167622
},{
"label": "La Bandera", "lat": 30.626827, "lng": -110.836354
},{
"label": "Rancho Franco", "lat": 30.818075, "lng": -111.191552
},{
"label": "Esperanza Valle", "lat": 30.791406, "lng": -111.220195
},{
"label": "Antonio Contreras", "lat": 30.578294, "lng": -110.907623
},{
"label": "El Rincón de San Francisco", "lat": 30.690096, "lng": -110.973947
},{
"label": "La Jojobita (La Jojoba)", "lat": 30.786056, "lng": -111.269921
},{
"label": "El Tigre", "lat": 30.532656, "lng": -110.933771
},{
"label": "Carlos Artemio Verdugo", "lat": 30.590177, "lng": -110.916746
},{
"label": "El Pozo Nuevo", "lat": 30.693597, "lng": -111.108895
},{
"label": "Familia Ortiz Moreno", "lat": 30.617402, "lng": -111.019611
},{
"label": "Santa Elena", "lat": 30.754891, "lng": -111.185014
},{
"label": "La Pitahaya", "lat": 30.687083, "lng": -110.924334
},{
"label": "San Judas", "lat": 30.671505, "lng": -110.949067
},{
"label": "El Alambre", "lat": 30.678196, "lng": -110.939961
},{
"label": "Mario Castro", "lat": 30.610126, "lng": -111.017171
},{
"label": "Santa Margarita", "lat": 30.818771, "lng": -111.104702
},{
"label": "Los Carrillos", "lat": 30.604407, "lng": -111.020502
},{
"label": "Las Aguilillas", "lat": 30.505626, "lng": -110.905181
},{
"label": "El Potrero", "lat": 30.562049, "lng": -110.872961
},{
"label": "La Montieleña", "lat": 30.690782, "lng": -110.936568
},{
"label": "El Peñasco", "lat": 30.605476, "lng": -111.017777
},{
"label": "El Tasícuri", "lat": 30.662016, "lng": -110.935565
},{
"label": "Pablo Torres", "lat": 30.698676, "lng": -110.971855
},{
"label": "La Compuerta", "lat": 31.03099, "lng": -111.191793
},{
"label": "El Volantín", "lat": 30.737902, "lng": -111.221458
},{
"label": "Arnulfo Javalera García", "lat": 30.560031, "lng": -110.892745
},{
"label": "Pozo Nuevo", "lat": 30.611609, "lng": -110.87726
},{
"label": "La Taza", "lat": 30.723865, "lng": -111.161291
},{
"label": "Las Parrillas", "lat": 30.566142, "lng": -110.88967
},{
"label": "La Moraga", "lat": 30.668949, "lng": -111.133493
},{
"label": "La Garita", "lat": 30.764887, "lng": -111.138179
},{
"label": "El Tule", "lat": 30.721685, "lng": -110.994151
},{
"label": "La Pasadita", "lat": 30.568333, "lng": -110.905624
},{
"label": "Familia Beltrán", "lat": 30.679462, "lng": -111.119553
},{
"label": "Arturo Mendoza", "lat": 30.726581, "lng": -111.152046
},{
"label": "José Manuel Moreno", "lat": 30.535825, "lng": -110.908084
},{
"label": "Rancho Guadalupe", "lat": 30.785416, "lng": -111.190967
},{
"label": "El Chino", "lat": 30.694089, "lng": -111.150199
},{
"label": "San Gabriel", "lat": 30.684735, "lng": -110.972228
},{
"label": "Juan Pedro Monteverde", "lat": 30.814196, "lng": -111.187871
},{
"label": "El Manchón de Casas", "lat": 30.696118, "lng": -110.938166
},{
"label": "El Chasco", "lat": 30.568903, "lng": -110.901593
},{
"label": "La Tinaja Prieta", "lat": 30.659823, "lng": -110.862488
},{
"label": "Bellavista", "lat": 30.747717, "lng": -111.140601
},{
"label": "La Esperanza", "lat": 30.703045, "lng": -111.036176
},{
"label": "La Jojoba", "lat": 30.743354, "lng": -111.041217
},{
"label": "Óscar Contreras", "lat": 30.602718, "lng": -110.932963
},{
"label": "El Mezquite", "lat": 30.838314, "lng": -111.091544
},{
"label": "Rancho Fernando Aguirre", "lat": 30.576581, "lng": -110.910254
},{
"label": "La Zarza", "lat": 30.613818, "lng": -110.955009
},{
"label": "El Chinal", "lat": 30.663344, "lng": -110.8301
},{
"label": "El Sauce", "lat": 30.771528, "lng": -111.184171
},{
"label": "Agua Blanca", "lat": 30.506834, "lng": -110.871956
}]