[{
"label": "Zacazonapa (El Rancho los Pilinques)", "lat": 18.453211, "lng": -99.431309
},{
"label": "Los Sauces", "lat": 18.426971, "lng": -99.295093
},{
"label": "Tlajocopan", "lat": 18.408977, "lng": -99.437113
},{
"label": "Juan Ocampo Bahena", "lat": 18.468521, "lng": -99.410878
},{
"label": "Venta de la Negra", "lat": 18.471786, "lng": -99.429937
},{
"label": "San Isidro (La Hacienda de San Isidro)", "lat": 18.546287, "lng": -99.417877
},{
"label": "El Aguacate [Antena de Microondas]", "lat": 18.445091, "lng": -99.415044
},{
"label": "Los Limones", "lat": 18.514708, "lng": -99.438625
},{
"label": "Huerta Juan Téllez (El Paso)", "lat": 18.466103, "lng": -99.398614
},{
"label": "Coxcatlán", "lat": 18.495178, "lng": -99.459945
},{
"label": "Las Mesas", "lat": 18.461157, "lng": -99.394841
},{
"label": "El Salitre", "lat": 18.437032, "lng": -99.327778
},{
"label": "Rancho Don Agustín", "lat": 18.454034, "lng": -99.397093
},{
"label": "La Fundición", "lat": 18.448596, "lng": -99.413041
},{
"label": "El Guerrerense [Restaurante]", "lat": 18.555761, "lng": -99.427873
},{
"label": "El Amate del Encanto", "lat": 18.426353, "lng": -99.475513
},{
"label": "Loma la Carrera", "lat": 18.445471, "lng": -99.349469
},{
"label": "Las Enramadas", "lat": 18.433458, "lng": -99.285592
},{
"label": "Las Mesas (Cerro Frío)", "lat": 18.457065, "lng": -99.289484
},{
"label": "La Bodega", "lat": 18.525089, "lng": -99.443344
},{
"label": "El Zapote", "lat": 18.468193, "lng": -99.330556
},{
"label": "El Amate Pollero", "lat": 18.440707, "lng": -99.42108
},{
"label": "Los Redondeados", "lat": 18.41628, "lng": -99.399124
},{
"label": "Buenavista de Cuéllar", "lat": 18.457887, "lng": -99.405342
},{
"label": "El Comal [El Paraje del Comal]", "lat": 18.456993, "lng": -99.282752
},{
"label": "Santa Fe Tepetlapa", "lat": 18.548318, "lng": -99.422036
},{
"label": "Los Pinos", "lat": 18.483225, "lng": -99.422808
},{
"label": "Bar Azteca [Restaurante]", "lat": 18.523546, "lng": -99.438332
},{
"label": "Agua del Toro", "lat": 18.447984, "lng": -99.448271
},{
"label": "El Platanal (El Platanar)", "lat": 18.501748, "lng": -99.422588
},{
"label": "San Rafael (La Alberca)", "lat": 18.5138, "lng": -99.411415
},{
"label": "Rincón de las Nueces", "lat": 18.503568, "lng": -99.401379
},{
"label": "Pozo Hondo (San Nicolás)", "lat": 18.554979, "lng": -99.449243
},{
"label": "Los Epazotes", "lat": 18.460769, "lng": -99.343026
},{
"label": "Zacapalco", "lat": 18.538162, "lng": -99.443603
},{
"label": "Las Mesas (Rancho Alegre)", "lat": 18.41377, "lng": -99.422476
},{
"label": "San Martín", "lat": 18.471174, "lng": -99.486813
},{
"label": "Cieneguillas", "lat": 18.411668, "lng": -99.476164
},{
"label": "Pimentel", "lat": 18.435448, "lng": -99.471366
},{
"label": "La Estancia (La Estancia de las Vacas)", "lat": 18.43884, "lng": -99.390517
},{
"label": "Luis Chávez Merlo", "lat": 18.465073, "lng": -99.424204
},{
"label": "Zozoquitla", "lat": 18.422659, "lng": -99.473171
},{
"label": "El Campamento la Ocho", "lat": 18.557668, "lng": -99.414978
},{
"label": "Palmillas", "lat": 18.52278, "lng": -99.426102
},{
"label": "Atexca", "lat": 18.396847, "lng": -99.456259
},{
"label": "Las Flores", "lat": 18.49091, "lng": -99.418748
},{
"label": "El Encino", "lat": 18.523308, "lng": -99.408795
},{
"label": "Los Amates", "lat": 18.41762, "lng": -99.489847
},{
"label": "San Lucas", "lat": 18.397345, "lng": -99.466149
},{
"label": "El Rodeo", "lat": 18.444084, "lng": -99.339364
},{
"label": "La Peña Blanca (El Rincón)", "lat": 18.485382, "lng": -99.432702
},{
"label": "Las Joyas (La Parada del Caballo)", "lat": 18.496289, "lng": -99.417731
},{
"label": "El Puente [Granja Avícola el Peñón Módulo]", "lat": 18.41886, "lng": -99.475293
},{
"label": "La Escondida (Rancho la Escondida)", "lat": 18.536986, "lng": -99.430858
},{
"label": "El Carrizalillo", "lat": 18.42676, "lng": -99.422376
},{
"label": "Rancho el Respaldo", "lat": 18.46727, "lng": -99.402924
},{
"label": "La Escondida (Rancho Escondida)", "lat": 18.45103, "lng": -99.287138
},{
"label": "La Huizachera", "lat": 18.404613, "lng": -99.411872
},{
"label": "Los Sabinos", "lat": 18.520189, "lng": -99.467806
},{
"label": "El Aguacate", "lat": 18.442557, "lng": -99.417
},{
"label": "La Parada de la Venta (Rancho Rodolfo Uribe)", "lat": 18.478091, "lng": -99.425959
},{
"label": "La Cumbre (El Puerto)", "lat": 18.401507, "lng": -99.484085
},{
"label": "Agua Bendita", "lat": 18.519, "lng": -99.432937
},{
"label": "Ixtlahuaca", "lat": 18.53242, "lng": -99.441345
},{
"label": "Rancho Nuevo", "lat": 18.454192, "lng": -99.347823
}]