[{
"label": "Lomas San Joaquín", "lat": 21.602903, "lng": -98.965373
},{
"label": "Tamaletom Primera Sección", "lat": 21.603661, "lng": -98.936207
},{
"label": "Altamira", "lat": 21.672347, "lng": -98.973362
},{
"label": "El Vado", "lat": 21.592489, "lng": -98.903277
},{
"label": "Palmira Nuevo", "lat": 21.67753, "lng": -98.972562
},{
"label": "La Noria", "lat": 21.629717, "lng": -98.976909
},{
"label": "Tancanhuitz", "lat": 21.597319, "lng": -98.966388
},{
"label": "Pechpechtla", "lat": 21.576043, "lng": -98.909104
},{
"label": "Atempa", "lat": 21.552269, "lng": -98.922891
},{
"label": "Jópoymom Primera Sección", "lat": 21.667395, "lng": -98.949915
},{
"label": "Xolol Tancoltze Segunda Sección", "lat": 21.591574, "lng": -98.992763
},{
"label": "Bethania", "lat": 21.596254, "lng": -98.990466
},{
"label": "Zojualo", "lat": 21.560569, "lng": -98.910127
},{
"label": "Ojtlayo", "lat": 21.569167, "lng": -98.933056
},{
"label": "Tzépacab Segunda Sección Tzapicté", "lat": 21.579579, "lng": -98.888538
},{
"label": "Dos Arbolitos", "lat": 21.6331, "lng": -98.984374
},{
"label": "El Capricho", "lat": 21.593418, "lng": -98.954599
},{
"label": "María Eva Villaseñor", "lat": 21.665106, "lng": -98.974221
},{
"label": "Las Armas", "lat": 21.697616, "lng": -98.967225
},{
"label": "El Juk", "lat": 21.601866, "lng": -98.913819
},{
"label": "Ejido la Ceiba", "lat": 21.687222, "lng": -98.99703
},{
"label": "El Izote", "lat": 21.590327, "lng": -98.9202
},{
"label": "Cuatechic", "lat": 21.563842, "lng": -98.939452
},{
"label": "Cuatuchco Tuzantla", "lat": 21.570304, "lng": -98.911518
},{
"label": "Temamtipa", "lat": 21.55489, "lng": -98.925297
},{
"label": "Las Jacarandas", "lat": 21.60146, "lng": -98.98811
},{
"label": "La Cuesta", "lat": 21.57753, "lng": -98.92272
},{
"label": "Al Tén", "lat": 21.599804, "lng": -98.976919
},{
"label": "Lomas de Santa Cirenia", "lat": 21.590038, "lng": -98.964746
},{
"label": "El Chijol", "lat": 21.569369, "lng": -98.888835
},{
"label": "Los Pinolillos (Oscar Suárez)", "lat": 21.624167, "lng": -98.978889
},{
"label": "El Colorado", "lat": 21.596039, "lng": -98.953281
},{
"label": "Ermilo Ramírez Guzmán (Las Armas)", "lat": 21.707874, "lng": -98.963034
},{
"label": "Colaltitla", "lat": 21.558529, "lng": -98.9405
},{
"label": "Chacatitla Tercera Sección", "lat": 21.590112, "lng": -98.956309
},{
"label": "Cuajenco Primera Sección", "lat": 21.575828, "lng": -98.954433
},{
"label": "El Tamarindo (Cacoyole)", "lat": 21.555956, "lng": -98.937345
},{
"label": "Crucerito la Cuesta", "lat": 21.624703, "lng": -98.977674
},{
"label": "Aljuantzintla", "lat": 21.556024, "lng": -98.913169
},{
"label": "Tzitzol", "lat": 21.60841, "lng": -98.92679
},{
"label": "Cerro del Guajolote", "lat": 21.617927, "lng": -98.979505
},{
"label": "It'il Mom", "lat": 21.593218, "lng": -98.908953
},{
"label": "Timel Já", "lat": 21.593864, "lng": -98.934546
},{
"label": "Tepeyac", "lat": 21.566425, "lng": -98.919124
},{
"label": "Xocoyo", "lat": 21.574722, "lng": -98.921667
},{
"label": "Las Tres Flores", "lat": 21.598659, "lng": -98.990094
},{
"label": "El Sabino", "lat": 21.581581, "lng": -98.892758
},{
"label": "Mexcala", "lat": 21.579428, "lng": -98.977185
},{
"label": "Octzén San Agustín", "lat": 21.674359, "lng": -99.011325
},{
"label": "Acayo", "lat": 21.566884, "lng": -98.938078
},{
"label": "Tomás Enríquez", "lat": 21.62343, "lng": -98.946979
},{
"label": "Tancoltze Ojox (Tercera Sección)", "lat": 21.587706, "lng": -98.978571
},{
"label": "Ojox (Tamaletom Segunda Sección)", "lat": 21.603286, "lng": -98.939883
},{
"label": "Camanco", "lat": 21.574635, "lng": -98.927497
},{
"label": "Los Pinolillos", "lat": 21.622107, "lng": -98.980476
},{
"label": "Barrio el Tamarindo", "lat": 21.58516, "lng": -98.934983
},{
"label": "La Garza (Pequetzén de la Garza)", "lat": 21.64151, "lng": -98.935267
},{
"label": "Escuayo", "lat": 21.579744, "lng": -98.931668
},{
"label": "Cuayo", "lat": 21.568265, "lng": -98.895938
},{
"label": "Tlamaya", "lat": 21.555115, "lng": -98.917386
},{
"label": "Alojox Mom", "lat": 21.596852, "lng": -98.926534
},{
"label": "Callejón las Lajas", "lat": 21.595147, "lng": -98.972338
},{
"label": "Rancho el Sacrificio", "lat": 21.590338, "lng": -98.924701
},{
"label": "El Crucero (Crucerito)", "lat": 21.614945, "lng": -98.986611
},{
"label": "José Antonio Gutiérrez", "lat": 21.629167, "lng": -98.985278
},{
"label": "Jopoy", "lat": 21.603899, "lng": -98.9611
},{
"label": "Alkiná Mom", "lat": 21.607014, "lng": -98.923314
},{
"label": "Alfredo Martínez", "lat": 21.648721, "lng": -98.979482
},{
"label": "Tzé Pakáb Primera Sección", "lat": 21.589926, "lng": -98.905268
},{
"label": "Xoteyo", "lat": 21.582766, "lng": -98.929406
},{
"label": "Cuashilotitla", "lat": 21.555278, "lng": -98.938333
},{
"label": "San José Pequetzén", "lat": 21.629569, "lng": -98.959471
},{
"label": "Rancho la Tijera", "lat": 21.626999, "lng": -98.985081
},{
"label": "Colonia Omar San Román", "lat": 21.623456, "lng": -98.980892
},{
"label": "Camanco (Tepeixco)", "lat": 21.578056, "lng": -98.9275
},{
"label": "Tlamimil", "lat": 21.557845, "lng": -98.922041
},{
"label": "Tenexio", "lat": 21.581944, "lng": -98.9375
},{
"label": "Mexcala Cuaymom", "lat": 21.58138, "lng": -98.970864
},{
"label": "David Azuara", "lat": 21.649319, "lng": -98.956823
},{
"label": "La Maceta", "lat": 21.649506, "lng": -98.978561
},{
"label": "Zapuyo", "lat": 21.556709, "lng": -98.938244
},{
"label": "Tamaletóm Tercera Sección", "lat": 21.598679, "lng": -98.944306
},{
"label": "Tzac Anam", "lat": 21.611681, "lng": -98.968484
},{
"label": "Tzutzocolo", "lat": 21.554784, "lng": -98.935391
},{
"label": "Xilozochio", "lat": 21.558889, "lng": -98.936389
},{
"label": "Cuatuchco Cuayo Piaxtla", "lat": 21.56872, "lng": -98.908209
},{
"label": "El Abandonado", "lat": 21.647093, "lng": -98.978886
},{
"label": "Cuaquentla", "lat": 21.564167, "lng": -98.943333
},{
"label": "Lay Mom", "lat": 21.602733, "lng": -98.918324
},{
"label": "Poytzén", "lat": 21.629409, "lng": -98.937222
},{
"label": "Tecamashochio", "lat": 21.553879, "lng": -98.923763
},{
"label": "La Cruz", "lat": 21.583857, "lng": -98.898469
},{
"label": "El Mango", "lat": 21.595556, "lng": -98.921667
},{
"label": "El Sacrificio", "lat": 21.624464, "lng": -98.972872
},{
"label": "Coyol Já (Tzác Anam)", "lat": 21.609569, "lng": -98.955923
},{
"label": "La Zanja", "lat": 21.554943, "lng": -98.927378
},{
"label": "Jol Ja", "lat": 21.606246, "lng": -98.935291
},{
"label": "Aldzulup Poytzén", "lat": 21.672121, "lng": -98.987615
},{
"label": "Rancho San Lorenzo", "lat": 21.645686, "lng": -98.980345
},{
"label": "Chacatitla Primera Sección", "lat": 21.588896, "lng": -98.951046
},{
"label": "Tlalcintla", "lat": 21.575802, "lng": -98.934629
},{
"label": "Cuajenco Tercera Sección", "lat": 21.579935, "lng": -98.961314
},{
"label": "La Zanja (Cuachenchenco)", "lat": 21.556176, "lng": -98.92738
},{
"label": "Tempexquistitla", "lat": 21.583889, "lng": -98.916842
},{
"label": "Crucero de Xolol", "lat": 21.593934, "lng": -98.99572
},{
"label": "Escuela Vieja", "lat": 21.609164, "lng": -98.950173
},{
"label": "Socohuijio", "lat": 21.561524, "lng": -98.941577
},{
"label": "Tlapani (Téxcatl)", "lat": 21.587853, "lng": -98.927931
},{
"label": "El Dorado", "lat": 21.695843, "lng": -98.964242
},{
"label": "Fracción la Cuesta", "lat": 21.615238, "lng": -98.974187
},{
"label": "El Paraíso", "lat": 21.660423, "lng": -98.976363
},{
"label": "Choy", "lat": 21.606203, "lng": -98.942993
},{
"label": "Mul Té", "lat": 21.606176, "lng": -98.946226
},{
"label": "Barrio la Laguna", "lat": 21.583491, "lng": -98.933675
},{
"label": "La Chaca", "lat": 21.579084, "lng": -98.907101
},{
"label": "Atlatentle", "lat": 21.563056, "lng": -98.943889
},{
"label": "Tolojco", "lat": 21.562731, "lng": -98.924676
},{
"label": "Antonio Flores", "lat": 21.627731, "lng": -98.98601
},{
"label": "May Té", "lat": 21.602222, "lng": -98.937778
},{
"label": "Damaso Arrieta (La Laja)", "lat": 21.574988, "lng": -98.900251
},{
"label": "Barrio el Mango", "lat": 21.59106, "lng": -98.909641
},{
"label": "Colonia Lázaro Cárdenas", "lat": 21.566389, "lng": -98.943333
},{
"label": "Cahueitetl", "lat": 21.560833, "lng": -98.940556
},{
"label": "El Falsete", "lat": 21.591449, "lng": -98.926965
},{
"label": "Capúchotl", "lat": 21.564167, "lng": -98.942222
},{
"label": "Hac Mom (Tamaletom Segunda Sección)", "lat": 21.601557, "lng": -98.921673
},{
"label": "Adán", "lat": 21.650593, "lng": -98.978983
},{
"label": "Chiapa", "lat": 21.56, "lng": -98.940556
},{
"label": "Tlaehuaya", "lat": 21.581792, "lng": -98.941632
},{
"label": "Haba", "lat": 21.603581, "lng": -98.938253
},{
"label": "Acuitlatipa", "lat": 21.552716, "lng": -98.927957
},{
"label": "Jópoymom Segunda Sección", "lat": 21.683136, "lng": -98.952187
},{
"label": "La Figura", "lat": 21.626944, "lng": -98.986667
},{
"label": "Rancho Pequetzén", "lat": 21.627332, "lng": -98.951263
},{
"label": "Chiltzapuyo", "lat": 21.583024, "lng": -98.937446
},{
"label": "Rancho Diego Ignacio Hernández", "lat": 21.564479, "lng": -98.924821
},{
"label": "Apigya II", "lat": 21.555858, "lng": -98.928467
},{
"label": "Xolol Bethania", "lat": 21.600134, "lng": -98.986832
},{
"label": "Chapalamel", "lat": 21.562754, "lng": -98.913925
},{
"label": "Tzicayo", "lat": 21.561667, "lng": -98.927778
},{
"label": "Cuayo Piaxtla", "lat": 21.561389, "lng": -98.921389
},{
"label": "Tecalco", "lat": 21.563611, "lng": -98.943889
},{
"label": "Poxol", "lat": 21.597046, "lng": -98.916796
},{
"label": "Rancho los Girasoles", "lat": 21.603832, "lng": -98.98651
},{
"label": "Lalasho", "lat": 21.554754, "lng": -98.933034
},{
"label": "Unup Juk Tzepacab", "lat": 21.595142, "lng": -98.915825
},{
"label": "Cruztujub", "lat": 21.635454, "lng": -98.924811
},{
"label": "Guadalupe Victoria", "lat": 21.621171, "lng": -98.944216
},{
"label": "Linares", "lat": 21.660616, "lng": -98.940316
},{
"label": "La Pitaya", "lat": 21.653546, "lng": -98.977998
},{
"label": "Pemoch (Pemucho)", "lat": 21.566111, "lng": -98.942222
},{
"label": "El Caliche", "lat": 21.596084, "lng": -98.959023
},{
"label": "Toltitla", "lat": 21.557778, "lng": -98.919167
},{
"label": "Chacatitla Segunda Sección", "lat": 21.588125, "lng": -98.951009
},{
"label": "San Francisco [Rancho]", "lat": 21.640808, "lng": -98.948154
},{
"label": "Camino Viejo (La Loma)", "lat": 21.638153, "lng": -98.976566
},{
"label": "La Quebradora", "lat": 21.593819, "lng": -98.945401
},{
"label": "Tzoté Mom", "lat": 21.599551, "lng": -98.936729
},{
"label": "Pila Mom", "lat": 21.608531, "lng": -98.93565
},{
"label": "Oxitipa", "lat": 21.623651, "lng": -98.990081
},{
"label": "Tamarindo", "lat": 21.65982, "lng": -98.938488
},{
"label": "Jorge Andablo Villanueva (La Cuesta)", "lat": 21.61001, "lng": -98.971453
},{
"label": "Barrio Tzicayo", "lat": 21.584935, "lng": -98.938266
},{
"label": "Cachiatl", "lat": 21.567778, "lng": -98.938889
},{
"label": "Tlalzintla", "lat": 21.565939, "lng": -98.944979
},{
"label": "Crucero Marcelino Zamarrón", "lat": 21.622959, "lng": -98.986701
},{
"label": "Sholinte", "lat": 21.597783, "lng": -98.946486
},{
"label": "Atzumpac", "lat": 21.569722, "lng": -98.939167
},{
"label": "Tancoltze Primera Sección", "lat": 21.583302, "lng": -98.979095
},{
"label": "Cacorus", "lat": 21.573716, "lng": -98.929239
},{
"label": "Bolchal", "lat": 21.59257, "lng": -98.916173
},{
"label": "El Coco", "lat": 21.579097, "lng": -98.908935
},{
"label": "Puyecapa", "lat": 21.560278, "lng": -98.925556
},{
"label": "Acuapichco", "lat": 21.566111, "lng": -98.941944
},{
"label": "Epifanio Solís", "lat": 21.62845, "lng": -98.985071
},{
"label": "Tzejelja", "lat": 21.604444, "lng": -98.914167
},{
"label": "Tepetzintla", "lat": 21.568333, "lng": -98.938056
},{
"label": "Tzabac", "lat": 21.598889, "lng": -98.911944
},{
"label": "Casúhuatl", "lat": 21.566667, "lng": -98.941111
},{
"label": "Tuzantla", "lat": 21.574223, "lng": -98.913735
},{
"label": "Chiquilixco", "lat": 21.57844, "lng": -98.91613
},{
"label": "Tlajcutepec", "lat": 21.572778, "lng": -98.925278
},{
"label": "Zacapetlayo Tuzantla", "lat": 21.570833, "lng": -98.925833
},{
"label": "Los Carrizos", "lat": 21.574546, "lng": -98.895034
},{
"label": "Barrio Xochimilco", "lat": 21.590271, "lng": -98.968065
},{
"label": "Cuatlamayán", "lat": 21.588504, "lng": -98.936901
},{
"label": "Cahamatl", "lat": 21.565833, "lng": -98.926111
},{
"label": "Hual Ja", "lat": 21.603333, "lng": -98.941389
},{
"label": "Copalitos", "lat": 21.617731, "lng": -98.967394
},{
"label": "Shiliapa", "lat": 21.565718, "lng": -98.913784
},{
"label": "San Isidro (Santo Domingo)", "lat": 21.630059, "lng": -98.984667
},{
"label": "Tzahib Mom", "lat": 21.602081, "lng": -98.938958
},{
"label": "Rancho los Gavilanes", "lat": 21.617254, "lng": -98.988091
},{
"label": "Alhuitot (Thimantzén)", "lat": 21.623269, "lng": -98.947848
},{
"label": "Tzajpiloco", "lat": 21.564644, "lng": -98.928365
},{
"label": "Palmira Viejo", "lat": 21.690723, "lng": -99.005366
},{
"label": "Hueyjajco", "lat": 21.568328, "lng": -98.928134
},{
"label": "Haytic (Pachuca)", "lat": 21.578615, "lng": -98.941018
},{
"label": "Rancho San Isidro", "lat": 21.631649, "lng": -98.984013
},{
"label": "Colonia Primero de Mayo", "lat": 21.570681, "lng": -98.896445
},{
"label": "Zacapetlayo", "lat": 21.557222, "lng": -98.936667
},{
"label": "Chiapa Tuzantla", "lat": 21.574597, "lng": -98.917332
},{
"label": "Tzimpustello", "lat": 21.5825, "lng": -98.917222
},{
"label": "Ixojátl", "lat": 21.562643, "lng": -98.941066
},{
"label": "La Reforma", "lat": 21.591205, "lng": -98.93023
},{
"label": "Aguacpa", "lat": 21.56597, "lng": -98.927419
},{
"label": "Atzintla", "lat": 21.567948, "lng": -98.941669
},{
"label": "Chuche Mom", "lat": 21.608829, "lng": -98.947053
},{
"label": "La Campana", "lat": 21.590556, "lng": -98.936667
},{
"label": "El Molino", "lat": 21.658048, "lng": -98.976004
},{
"label": "Fracción O'ctzén", "lat": 21.616228, "lng": -98.955513
},{
"label": "Cruzatl", "lat": 21.568889, "lng": -98.941944
},{
"label": "Zacapetlayo Cuayo Piaxtla", "lat": 21.568625, "lng": -98.924012
},{
"label": "Santa Isabel", "lat": 21.663911, "lng": -98.965296
},{
"label": "Tlamimil (Tepechio)", "lat": 21.556749, "lng": -98.933333
},{
"label": "Apigya Uno", "lat": 21.560018, "lng": -98.930846
},{
"label": "La Loma", "lat": 21.587753, "lng": -98.917801
},{
"label": "Cuilocuayo", "lat": 21.563353, "lng": -98.936357
},{
"label": "El Rinconcito", "lat": 21.594667, "lng": -98.987928
},{
"label": "Cuajenco Segunda Sección", "lat": 21.580293, "lng": -98.95484
},{
"label": "La Esperanza", "lat": 21.582617, "lng": -98.91291
},{
"label": "Caojtlátl", "lat": 21.562269, "lng": -98.943905
},{
"label": "Tempexquistitla (José Eustacio Domínguez)", "lat": 21.58, "lng": -98.926389
},{
"label": "Tey Já", "lat": 21.597638, "lng": -98.924218
},{
"label": "Aldzulup", "lat": 21.617176, "lng": -98.926726
},{
"label": "Casa Verde (Ponda Rosa)", "lat": 21.604559, "lng": -98.987466
},{
"label": "Rancho el Paraíso", "lat": 21.573581, "lng": -99.002458
},{
"label": "Ana Teresa", "lat": 21.655388, "lng": -98.977535
},{
"label": "Hac Mom", "lat": 21.59866, "lng": -98.920168
},{
"label": "Tanjol Dhu't (La Entrada)", "lat": 21.594734, "lng": -98.94563
},{
"label": "Tlashich", "lat": 21.565, "lng": -98.937222
}]