[{
"label": "Onésimo Nieto", "lat": 16.409964, "lng": -98.356698
},{
"label": "La Huerta (La Finca)", "lat": 16.421913, "lng": -98.355279
},{
"label": "La Cueva del Coyote", "lat": 16.464511, "lng": -98.283666
},{
"label": "La Herradura", "lat": 16.426073, "lng": -98.307203
},{
"label": "El Puente", "lat": 16.41902, "lng": -98.336985
},{
"label": "Báscula Guadalupana", "lat": 16.433441, "lng": -98.317088
},{
"label": "Cerro Bofo", "lat": 16.426507, "lng": -98.318278
},{
"label": "Rigoberto Reyes", "lat": 16.402495, "lng": -98.272721
},{
"label": "El Manguito", "lat": 16.393241, "lng": -98.34391
},{
"label": "Félix Toribio", "lat": 16.420887, "lng": -98.309499
},{
"label": "Caseta Fiscal", "lat": 16.444033, "lng": -98.345376
},{
"label": "Santa María Cortijo", "lat": 16.450803, "lng": -98.285716
}]